README.rst
setup.py
aggregates/__init__.py
aggregates/conditional.py
django_conditional_aggregates.egg-info/PKG-INFO
django_conditional_aggregates.egg-info/SOURCES.txt
django_conditional_aggregates.egg-info/dependency_links.txt
django_conditional_aggregates.egg-info/pbr.json
django_conditional_aggregates.egg-info/top_level.txt