Metadata-Version: 1.0
Name: django-conditional-aggregates
Version: 0.1.0
Summary: Django aggregate functions which operate conditionally (i.e. generate SQL `CASE` statements)
Home-page: https://github.com/anentropic/django-conditional-aggregates
Author: Anentropic
Author-email: ego@anentropic.com
License: MIT
Platform: UNKNOWN
